abc_instantid/__init__.py
abc_instantid/apis.py
abc_instantid/apps.py
abc_instantid/models.py
abc_instantid/serializers.py
abc_instantid/migrations/0001_initial.py
abc_instantid/migrations/0002_auto_20240218_1504.py
abc_instantid/migrations/__init__.py
abc_instantid-0.0.4.dist-info/METADATA
abc_instantid-0.0.4.dist-info/WHEEL
abc_instantid-0.0.4.dist-info/top_level.txt
abc_instantid-0.0.4.dist-info/RECORD
