Metadata-Version: 2.1
Name: abc-instantid
Version: 0.0.4
Summary: instantid utils
Home-page: https://github.com/szuprefix/py-abc-instantid
Author: denishuang
Author-email: 2529465700@qq.com
License: MIT
Classifier: Environment :: Web Environment
Classifier: Intended Audience :: Developers
Classifier: Operating System :: OS Independent
Classifier: Topic :: Text Processing :: Indexing
Classifier: Topic :: Utilities
Classifier: Topic :: Internet
Classifier: Topic :: Software Development :: Libraries :: Python Modules
Classifier: Programming Language :: Python
Classifier: Programming Language :: Python :: 2
Classifier: Programming Language :: Python :: 2.7
Classifier: Programming Language :: Python :: 3
Classifier: Programming Language :: Python :: 3.5
Classifier: Programming Language :: Python :: 3.6
Classifier: Programming Language :: Python :: 3.7
Classifier: Programming Language :: Python :: 3.8
